BridgeFuncRecovery/__init__.py
BridgeFuncRecovery/main.py
BridgeFuncRecovery/result_analysis.py
BridgeFuncRecovery/utils.py
bridgefuncrecovery-0.1.1.dist-info/METADATA
bridgefuncrecovery-0.1.1.dist-info/WHEEL
bridgefuncrecovery-0.1.1.dist-info/top_level.txt
bridgefuncrecovery-0.1.1.dist-info/RECORD
