Metadata-Version: 2.4
Name: BridgeFuncRecovery
Version: 0.1.1
Summary: A Python package to model post-earthquake functional recovery of bridges.
Author-email: Chenhao Wu <chenhaowu@ucla.edu>, Henry V Burton <hvburton@ucla.edu>
Maintainer: Chenhao Wu, Henry V Burton, Navleen Kaur
Project-URL: Source,  https://github.com/wuch9920061/BridgeFuncRecovery
Requires-Python: >=3.6
Requires-Dist: numpy
Requires-Dist: pandas
Requires-Dist: scipy
Requires-Dist: matplotlib
